gopay/__init__.py
gopay/api.py
gopay/enums.py
gopay/http.py
gopay/models.py
gopay/payments.py
gopay/services.py
gopay/utils.py
gopay-2.2.5.dist-info/LICENSE
gopay-2.2.5.dist-info/METADATA
gopay-2.2.5.dist-info/WHEEL
gopay-2.2.5.dist-info/RECORD
