Metadata-Version: 2.1
Name: gopay
Version: 2.2.5
Summary: GoPay's Python SDK for Payments REST API
Home-page: https://github.com/gopaycommunity/gopay-python-api
License: MIT
Keywords: gopay,payments,sdk,rest,api
Author: GoPay
Author-email: integrace@gopay.cz
Requires-Python: >=3.9,<4.0
Classifier: Development Status :: 5 - Production/Stable
Classifier: Intended Audience :: Developers
Classifier: License :: OSI Approved :: MIT License
Classifier: Programming Language :: Python :: 3
Classifier: Programming Language :: Python :: 3.9
Classifier: Programming Language :: Python :: 3.10
Classifier: Programming Language :: Python :: 3.11
Classifier: Programming Language :: Python :: 3.12
Classifier: Topic :: Software Development :: Libraries :: Python Modules
Requires-Dist: deprecated (>=1.2.14,<2.0.0)
Requires-Dist: pydantic (>=2.8.2,<3.0.0)
Requires-Dist: requests (>=2.31.0,<3.0.0)
Requires-Dist: tomli (>=2.0.1,<3.0.0)
Project-URL: Documentation, https://doc.gopay.com
Project-URL: Repository, https://github.com/gopaycommunity/gopay-python-api
